{"code": "308818", "name": "幽门螺杆菌概念", "update_time": "2026-03-18", "stocks": [{"代码": "603222", "名称": "济民健康", "流通市值": 4631299224.3}, {"代码": "603387", "名称": "基蛋生物", "流通市值": 4787529200.48}, {"代码": "300858", "名称": "科拓生物", "流通市值": 3182734871.52}, {"代码": "688426", "名称": "康为世纪", "流通市值": 855013388}, {"代码": "300887", "名称": "谱尼测试", "流通市值": 4328256779}, {"代码": "300267", "名称": "尔康制药", "流通市值": 5632671888.36}, {"代码": "002742", "名称": "*ST三圣", "流通市值": 2420695768.26}, {"代码": "002923", "名称": "润都股份", "流通市值": 3971925579.87}, {"代码": "002793", "名称": "罗欣药业", "流通市值": 5223349004.64}, {"代码": "300639", "名称": "凯普生物", "流通市值": 4198436492.31}, {"代码": "300111", "名称": "向日葵", "流通市值": 5444901320.22}, {"代码": "301087", "名称": "可孚医疗", "流通市值": 11421195577.2}, {"代码": "300199", "名称": "翰宇药业", "流通市值": 13616442649.7}, {"代码": "300086", "名称": "康芝药业", "流通市值": 3847158417.06}, {"代码": "688767", "名称": "博拓生物", "流通市值": 5199786689.88}, {"代码": "002370", "名称": "亚太药业", "流通市值": 4839382269.7}, {"代码": "688067", "名称": "爱威科技", "流通市值": 1862520000}, {"代码": "301111", "名称": "粤万年青", "流通市值": 3129600000}, {"代码": "002030", "名称": "达安基因", "流通市值": 8645227557.12}, {"代码": "600420", "名称": "国药现代", "流通市值": 14444429892.84}, {"代码": "600774", "名称": "汉商集团", "流通市值": 2712547605.2}, {"代码": "603392", "名称": "万泰生物", "流通市值": 51397567482.6}, {"代码": "002038", "名称": "双鹭药业", "流通市值": 5213710430.28}, {"代码": "605388", "名称": "均瑶健康", "流通市值": 3975204080}, {"代码": "600351", "名称": "亚宝药业", "流通市值": 4601800305.9}, {"代码": "600566", "名称": "济川药业", "流通市值": 24636227878.8}, {"代码": "301190", "名称": "善水科技", "流通市值": 3732070680}, {"代码": "688317", "名称": "之江生物", "流通市值": 3768218360.39}, {"代码": "300404", "名称": "博济医药", "流通市值": 2845608417.21}, {"代码": "300463", "名称": "迈克生物", "流通市值": 5631111832}, {"代码": "301277", "名称": "新天地", "流通市值": 4795118832}, {"代码": "300406", "名称": "九强生物", "流通市值": 5309447975.55}, {"代码": "002675", "名称": "东诚药业", "流通市值": 9790367200.98}, {"代码": "300962", "名称": "中金辐照", "流通市值": 4593633007.8}, {"代码": "000623", "名称": "吉林敖东", "流通市值": 22224496513.38}, {"代码": "300584", "名称": "海辰药业", "流通市值": 3562785268.94}, {"代码": "603658", "名称": "安图生物", "流通市值": 20022723870.72}, {"代码": "000881", "名称": "中广核技", "流通市值": 7229858808}, {"代码": "002603", "名称": "以岭药业", "流通市值": 23254941421.71}, {"代码": "600572", "名称": "康恩贝", "流通市值": 11232903354.72}, {"代码": "688606", "名称": "奥泰生物", "流通市值": 5194481619.6}, {"代码": "300482", "名称": "万孚生物", "流通市值": 8405684189.28}, {"代码": "301060", "名称": "兰卫医学", "流通市值": 3738715701.66}, {"代码": "002086", "名称": "东方海洋", "流通市值": 3984840813.24}, {"代码": "300439", "名称": "美康生物", "流通市值": 2996403522.75}, {"代码": "603882", "名称": "金域医学", "流通市值": 12745727782.9}, {"代码": "002317", "名称": "众生药业", "流通市值": 13762426526.42}, {"代码": "002412", "名称": "汉森制药", "流通市值": 3415216700}, {"代码": "002223", "名称": "鱼跃医疗", "流通市值": 33685867016.12}, {"代码": "688799", "名称": "华纳药厂", "流通市值": 5806970400}, {"代码": "603739", "名称": "蔚蓝生物", "流通市值": 4033280124.04}, {"代码": "603108", "名称": "润达医疗", "流通市值": 8771495929.21}, {"代码": "605507", "名称": "国邦医药", "流通市值": 15501763890}, {"代码": "002898", "名称": "*ST赛隆", "流通市值": 1185784589.31}, {"代码": "000777", "名称": "中核科技", "流通市值": 9788478413.31}, {"代码": "300705", "名称": "九典制药", "流通市值": 5422653144.3}, {"代码": "002755", "名称": "奥赛康", "流通市值": 13625265135.68}, {"代码": "301096", "名称": "百诚医药", "流通市值": 4248638026.28}, {"代码": "300869", "名称": "康泰医学", "流通市值": 3620531748.06}, {"代码": "605199", "名称": "ST葫芦娃", "流通市值": 2708736251.04}, {"代码": "002940", "名称": "昂利康", "流通市值": 5586055330.05}, {"代码": "002728", "名称": "特一药业", "流通市值": 4182639240.6}, {"代码": "000756", "名称": "新华制药", "流通市值": 7638148451.41}, {"代码": "300194", "名称": "福安药业", "流通市值": 4125146360.16}, {"代码": "688319", "名称": "欧林生物", "流通市值": 10986592030}, {"代码": "600252", "名称": "中恒集团", "流通市值": 8438032135.5}, {"代码": "002907", "名称": "华森制药", "流通市值": 4246789461.6}, {"代码": "600530", "名称": "交大昂立", "流通市值": 4308555200}, {"代码": "000705", "名称": "浙江震元", "流通市值": 2557384011.57}, {"代码": "300006", "名称": "莱美药业", "流通市值": 5279104490}, {"代码": "688658", "名称": "悦康药业", "流通市值": 8496000000}, {"代码": "688253", "名称": "英诺特", "流通市值": 5308142245}, {"代码": "002422", "名称": "科伦药业", "流通市值": 43355365566}, {"代码": "603139", "名称": "康惠股份", "流通市值": 2764678400}]}