{"code": "301402", "name": "上海国企改革", "update_time": "2026-03-18", "stocks": [{"代码": "600619", "名称": "海立股份", "流通市值": 14797027462.5}, {"代码": "600754", "名称": "锦江酒店", "流通市值": 25949101964.32}, {"代码": "600649", "名称": "城投控股", "流通市值": 12522503840}, {"代码": "600675", "名称": "中华企业", "流通市值": 17231485693.35}, {"代码": "600748", "名称": "上实发展", "流通市值": 9388825120.28}, {"代码": "600827", "名称": "百联股份", "流通市值": 13926625305.6}, {"代码": "600009", "名称": "上海机场", "流通市值": 60344782897.35}, {"代码": "600848", "名称": "上海临港", "流通市值": 25231835357.42}, {"代码": "601607", "名称": "上海医药", "流通市值": 48281181911.55}, {"代码": "601083", "名称": "锦江航运", "流通市值": 2385734800}, {"代码": "600621", "名称": "华鑫股份", "流通市值": 16369676075.56}, {"代码": "600170", "名称": "上海建工", "流通市值": 26124662847.36}, {"代码": "600741", "名称": "华域汽车", "流通市值": 59491901578.08}, {"代码": "600104", "名称": "上汽集团", "流通市值": 168175909883.52}, {"代码": "600018", "名称": "上港集团", "流通市值": 120650468236.5}, {"代码": "002564", "名称": "天沃科技", "流通市值": 5892084712.22}, {"代码": "600820", "名称": "隧道股份", "流通市值": 20562388454.76}, {"代码": "600642", "名称": "申能股份", "流通市值": 44337947193.36}, {"代码": "601595", "名称": "上海电影", "流通市值": 11518740000}, {"代码": "688660", "名称": "电气风电", "流通市值": 19466667640}, {"代码": "600597", "名称": "光明乳业", "流通市值": 10903581921.33}, {"代码": "603153", "名称": "上海建科", "流通市值": 6721722138.4}, {"代码": "600833", "名称": "第一医药", "流通市值": 2793041064.44}, {"代码": "600073", "名称": "光明肉业", "流通市值": 6113996157.44}, {"代码": "600819", "名称": "耀皮玻璃", "流通市值": 5822371161.93}, {"代码": "688538", "名称": "和辉光电", "流通市值": 14092977526.25}, {"代码": "688247", "名称": "宣泰医药", "流通市值": 4420065000}, {"代码": "600662", "名称": "外服控股", "流通市值": 12452296982.64}, {"代码": "600822", "名称": "上海物贸", "流通市值": 4060516057}, {"代码": "600630", "名称": "龙头股份", "流通市值": 3543345718.98}, {"代码": "600834", "名称": "申通地铁", "流通市值": 4062520011.55}, {"代码": "600835", "名称": "上海机电", "流通市值": 19283517813}, {"代码": "600616", "名称": "金枫酒业", "流通市值": 3592556581.5}, {"代码": "600650", "名称": "锦江在线", "流通市值": 5596725874.75}, {"代码": "600626", "名称": "申达股份", "流通市值": 4886186111.1}, {"代码": "600651", "名称": "飞乐音响", "流通市值": 18175953108.75}, {"代码": "601200", "名称": "上海环境", "流通市值": 11712203183.7}, {"代码": "600119", "名称": "长江投资", "流通市值": 2257370886.6}, {"代码": "600841", "名称": "动力新科", "流通市值": 9095173500.48}, {"代码": "600708", "名称": "光明地产", "流通市值": 8812099973.16}, {"代码": "600278", "名称": "东方创业", "流通市值": 6809660500.17}, {"代码": "600676", "名称": "交运股份", "流通市值": 7950250457.12}, {"代码": "600637", "名称": "东方明珠", "流通市值": 34627568115.1}, {"代码": "600825", "名称": "新华传媒", "流通市值": 6342469249.5}, {"代码": "600826", "名称": "兰生股份", "流通市值": 7620127567.64}, {"代码": "300457", "名称": "赢合科技", "流通市值": 15652293003.1}, {"代码": "601727", "名称": "上海电气", "流通市值": 108746813662.32}, {"代码": "301289", "名称": "国缆检测", "流通市值": 4279599698}, {"代码": "600623", "名称": "华谊集团", "流通市值": 19897680204.88}, {"代码": "600602", "名称": "云赛智联", "流通市值": 22076926444.5}, {"代码": "600618", "名称": "氯碱化工", "流通市值": 10392782067.36}, {"代码": "600629", "名称": "华建集团", "流通市值": 20434829552}, {"代码": "600097", "名称": "开创国际", "流通市值": 2806910912.35}, {"代码": "688347", "名称": "华虹公司", "流通市值": 51694545000}]}